simikit/__init__.py
simikit/api.py
simikit/config.py
simikit/features/__init__.py
simikit/features/__init__.pyi
simikit/features/base.py
simikit/features/hash.py
simikit/features/transformer.py
simikit/metrics/__init__.py
simikit/metrics/__init__.pyi
simikit/metrics/vector_distance.py
simikit/utils/__init__.py
simikit/utils/error_catcher.py
simikit/utils/images.py
simikit/utils/logger.py
simikit/utils/timer.py
simikit-0.1.3.dist-info/licenses/LICENSE
simikit-0.1.3.dist-info/METADATA
simikit-0.1.3.dist-info/WHEEL
simikit-0.1.3.dist-info/top_level.txt
simikit-0.1.3.dist-info/RECORD
