Metadata-Version: 2.4
Name: simikit
Version: 0.1.3
Summary: Image Similarity Toolkit in Python
Project-URL: Homepage, https://github.com/yie1d/simikit
Classifier: Development Status :: 4 - Beta
Classifier: Intended Audience :: Developers
Classifier: Operating System :: POSIX :: Linux
Classifier: Operating System :: MacOS :: MacOS X
Classifier: Operating System :: Microsoft :: Windows
Classifier: Programming Language :: Python
Classifier: Programming Language :: Python :: 3
Classifier: Programming Language :: Python :: 3.11
Classifier: Programming Language :: Python :: 3.12
Classifier: Programming Language :: Python :: 3.13
Classifier: Programming Language :: Python :: 3.14
Classifier: Topic :: Software Development :: Libraries
Classifier: Topic :: Software Development :: Libraries :: Python Modules
Requires-Python: >=3.11
License-File: LICENSE
Requires-Dist: loguru>=0.7.3
Requires-Dist: pydantic>=2.11.2
Requires-Dist: pywavelets>=1.8.0
Requires-Dist: scikit-image>=0.25.2
Requires-Dist: torch>=2.6.0
Requires-Dist: transformers>=4.50.3
Dynamic: license-file
